[
  {
    "time": "2025-08-18T20:23:19.897Z",
    "price": "$4,357.93"
  },
  {
    "time": "2025-08-18T20:25:11.951Z",
    "price": "$4,351.95"
  },
  {
    "time": "2025-08-18T20:37:23.196Z",
    "price": "$4,347.15"
  },
  {
    "time": "2025-08-18T21:31:35.848Z",
    "price": "$4,355.29"
  },
  {
    "time": "2025-08-18T22:37:26.815Z",
    "price": "$4,377.91"
  },
  {
    "time": "2025-08-18T23:32:19.048Z",
    "price": "$4,330.20"
  },
  {
    "time": "2025-08-19T03:33:05.962Z",
    "price": "$4,256.32"
  },
  {
    "time": "2025-08-19T04:43:44.953Z",
    "price": "$4,229.31"
  },
  {
    "time": "2025-08-19T05:39:15.852Z",
    "price": "$4,243.16"
  }
]
